{
  "results_folder": "nemotron-nano-9b-v2-t1.0",
  "game_id": 4,
  "proposals": [
    {
      "items": [
        "A11",
        "A21",
        "A60",
        "B09",
        "B20",
        "B31",
        "B93",
        "B96",
        "C08",
        "C85"
      ],
      "weight": 2795,
      "utility_player1": 5148,
      "utility_player2": 5325,
      "normalized_u1": 93.2946719826024,
      "normalized_u2": 78.7139689578714,
      "harmonic_mean": 85.38633727028541,
      "normalized_harmonic_mean": 92.06645468768563,
      "pareto_optimum": true,
      "by": "Player 1",
      "turn": 2
    },
    {
      "items": [
        "A21",
        "A60",
        "B09",
        "B20",
        "B31",
        "B39",
        "B93",
        "B96",
        "C08",
        "C85"
      ],
      "weight": 2568,
      "utility_player1": 4345,
      "utility_player2": 6128,
      "normalized_u1": 78.74229793403407,
      "normalized_u2": 90.5838876570584,
      "harmonic_mean": 84.24903029635587,
      "normalized_harmonic_mean": 90.84017160389641,
      "pareto_optimum": false,
      "by": "Player 2",
      "turn": 2
    },
    {
      "items": [
        "A21",
        "A60",
        "B09",
        "B20",
        "B31",
        "B39",
        "B93",
        "B96",
        "C08",
        "C85"
      ],
      "weight": 2568,
      "utility_player1": 4345,
      "utility_player2": 6128,
      "normalized_u1": 78.74229793403407,
      "normalized_u2": 90.5838876570584,
      "harmonic_mean": 84.24903029635587,
      "normalized_harmonic_mean": 90.84017160389641,
      "pareto_optimum": false,
      "by": "Player 2",
      "turn": 3
    },
    {
      "items": [
        "A21",
        "A60",
        "B09",
        "B20",
        "B31",
        "B39",
        "B93",
        "B96",
        "C08",
        "C85"
      ],
      "weight": 2568,
      "utility_player1": 4345,
      "utility_player2": 6128,
      "normalized_u1": 78.74229793403407,
      "normalized_u2": 90.5838876570584,
      "harmonic_mean": 84.24903029635587,
      "normalized_harmonic_mean": 90.84017160389641,
      "pareto_optimum": false,
      "by": "Player 2",
      "turn": 4
    },
    {
      "items": [
        "A21",
        "A60",
        "B09",
        "B20",
        "B31",
        "B39",
        "B93",
        "B96",
        "C08",
        "C85"
      ],
      "weight": 2568,
      "utility_player1": 4345,
      "utility_player2": 6128,
      "normalized_u1": 78.74229793403407,
      "normalized_u2": 90.5838876570584,
      "harmonic_mean": 84.24903029635587,
      "normalized_harmonic_mean": 90.84017160389641,
      "pareto_optimum": false,
      "by": "Player 2",
      "turn": 5
    },
    {
      "items": [
        "A11",
        "A21",
        "A60",
        "B09",
        "B20",
        "B31",
        "B93",
        "B96",
        "C08",
        "C85"
      ],
      "weight": 2795,
      "utility_player1": 5148,
      "utility_player2": 5325,
      "normalized_u1": 93.2946719826024,
      "normalized_u2": 78.7139689578714,
      "harmonic_mean": 85.38633727028541,
      "normalized_harmonic_mean": 92.06645468768563,
      "pareto_optimum": true,
      "by": "Player 2",
      "turn": 6
    }
  ],
  "refusals": [
    {
      "items": [
        "A21",
        "A60",
        "B09",
        "B20",
        "B31",
        "B39",
        "B93",
        "B96",
        "C08",
        "C85"
      ],
      "weight": 2568,
      "utility_player1": 4345,
      "utility_player2": 6128,
      "normalized_u1": 78.74229793403407,
      "normalized_u2": 90.5838876570584,
      "harmonic_mean": 84.24903029635587,
      "normalized_harmonic_mean": 90.84017160389641,
      "pareto_optimum": false,
      "by": "Player 1",
      "turn": 3
    },
    {
      "items": [
        "A21",
        "A60",
        "B09",
        "B20",
        "B31",
        "B39",
        "B93",
        "B96",
        "C08",
        "C85"
      ],
      "weight": 2568,
      "utility_player1": 4345,
      "utility_player2": 6128,
      "normalized_u1": 78.74229793403407,
      "normalized_u2": 90.5838876570584,
      "harmonic_mean": 84.24903029635587,
      "normalized_harmonic_mean": 90.84017160389641,
      "pareto_optimum": false,
      "by": "Player 1",
      "turn": 4
    },
    {
      "items": [
        "A21",
        "A60",
        "B09",
        "B20",
        "B31",
        "B39",
        "B93",
        "B96",
        "C08",
        "C85"
      ],
      "weight": 2568,
      "utility_player1": 4345,
      "utility_player2": 6128,
      "normalized_u1": 78.74229793403407,
      "normalized_u2": 90.5838876570584,
      "harmonic_mean": 84.24903029635587,
      "normalized_harmonic_mean": 90.84017160389641,
      "pareto_optimum": false,
      "by": "Player 1",
      "turn": 5
    },
    {
      "items": [
        "A21",
        "A60",
        "B09",
        "B20",
        "B31",
        "B39",
        "B93",
        "B96",
        "C08",
        "C85"
      ],
      "weight": 2568,
      "utility_player1": 4345,
      "utility_player2": 6128,
      "normalized_u1": 78.74229793403407,
      "normalized_u2": 90.5838876570584,
      "harmonic_mean": 84.24903029635587,
      "normalized_harmonic_mean": 90.84017160389641,
      "pareto_optimum": false,
      "by": "Player 1",
      "turn": 6
    }
  ],
  "agreement": {
    "items": [
      "A21",
      "A60",
      "B09",
      "B20",
      "B31",
      "B39",
      "B93",
      "B96",
      "C08",
      "C85"
    ],
    "weight": 2568,
    "utility_player1": 4345,
    "utility_player2": 6128,
    "normalized_u1": 78.74229793403407,
    "normalized_u2": 90.5838876570584,
    "harmonic_mean": 84.24903029635587,
    "normalized_harmonic_mean": 90.84017160389641,
    "pareto_optimum": false,
    "by": "Player 2",
    "turn": 8
  },
  "max_weight": 2984,
  "scores": {
    "player1_score": 4345,
    "player2_score": 6128,
    "normalized_u1": 78.74229793403407,
    "normalized_u2": 90.5838876570584,
    "harmonic_mean": 84.24903029635587,
    "normalized_harmonic_mean": 90.84017160389641,
    "episode_score": 12.5,
    "pareto_optimum": false,
    "pareto_adherence_rate": 0.3333333333333333
  },
  "max_u1": 5518,
  "max_u2": 6765,
  "max_harmonic": 92.74424388333297,
  "nb_proposals": 6,
  "player1_optimum": {
    "items": [
      "A11",
      "A60",
      "A82",
      "B09",
      "B20",
      "B31",
      "B93",
      "B96",
      "C08",
      "C85"
    ],
    "utility_player1": 5518,
    "utility_player2": 5025,
    "pareto_optimum": true
  },
  "player2_optimum": {
    "items": [
      "A21",
      "A60",
      "A82",
      "B09",
      "B20",
      "B39",
      "B93",
      "B96",
      "C81",
      "C85"
    ],
    "utility_player1": 3679,
    "utility_player2": 6765,
    "pareto_optimum": true
  },
  "global_optimum": {
    "items": [
      "A21",
      "A60",
      "A82",
      "B09",
      "B20",
      "B31",
      "B39",
      "B93",
      "B96",
      "C08",
      "C85"
    ],
    "utility_player1": 4853,
    "utility_player2": 6636,
    "harmonic_mean": 92.74424388333297,
    "pareto_optimum": true
  }
}