{
  "results_folder": "llama-3.3-70b-instruct-t1.0",
  "game_id": 2,
  "proposals": [
    {
      "items": [
        "A42",
        "A59",
        "A69",
        "B36",
        "B85"
      ],
      "weight": 4372,
      "utility_player1": 4852,
      "utility_player2": 4852,
      "normalized_u1": 42.08152645273201,
      "normalized_u2": 42.08152645273201,
      "harmonic_mean": 42.08152645273201,
      "normalized_harmonic_mean": 42.08152645273201,
      "pareto_optimum": null,
      "by": "Player 1",
      "turn": 1
    },
    {
      "items": [
        "A59",
        "A69",
        "A90",
        "B36",
        "C72"
      ],
      "weight": 3647,
      "utility_player1": 4127,
      "utility_player2": 4127,
      "normalized_u1": 35.79358196010408,
      "normalized_u2": 35.79358196010408,
      "harmonic_mean": 35.79358196010408,
      "normalized_harmonic_mean": 35.79358196010408,
      "pareto_optimum": null,
      "by": "Player 1",
      "turn": 2
    },
    {
      "items": [
        "A42",
        "A59",
        "A69",
        "B36",
        "C51"
      ],
      "weight": 4072,
      "utility_player1": 4552,
      "utility_player2": 4552,
      "normalized_u1": 39.479618386817,
      "normalized_u2": 39.479618386817,
      "harmonic_mean": 39.479618386817,
      "normalized_harmonic_mean": 39.479618386817,
      "pareto_optimum": null,
      "by": "Player 2",
      "turn": 2
    },
    {
      "items": [
        "A42",
        "A59",
        "A69",
        "B36",
        "B85",
        "C51"
      ],
      "weight": 5034,
      "utility_player1": 5610,
      "utility_player2": 5610,
      "normalized_u1": 48.655680832610585,
      "normalized_u2": 48.655680832610585,
      "harmonic_mean": 48.65568083261059,
      "normalized_harmonic_mean": 48.655680832610585,
      "pareto_optimum": null,
      "by": "Player 1",
      "turn": 3
    },
    {
      "items": [
        "A42",
        "A59",
        "A69",
        "A90",
        "B36",
        "B85",
        "C51"
      ],
      "weight": 5653,
      "utility_player1": 6325,
      "utility_player2": 6325,
      "normalized_u1": 54.856895056374675,
      "normalized_u2": 54.856895056374675,
      "harmonic_mean": 54.856895056374675,
      "normalized_harmonic_mean": 54.856895056374675,
      "pareto_optimum": null,
      "by": "Player 2",
      "turn": 3
    }
  ],
  "refusals": [
    {
      "items": [
        "A42",
        "A59",
        "A69",
        "B36",
        "B85"
      ],
      "weight": 4372,
      "utility_player1": 4852,
      "utility_player2": 4852,
      "normalized_u1": 42.08152645273201,
      "normalized_u2": 42.08152645273201,
      "harmonic_mean": 42.08152645273201,
      "normalized_harmonic_mean": 42.08152645273201,
      "pareto_optimum": null,
      "by": "Player 2",
      "turn": 1
    }
  ],
  "agreement": {
    "items": [
      "A42",
      "A59",
      "A69",
      "A90",
      "B36",
      "B85",
      "C51"
    ],
    "weight": 5653,
    "utility_player1": 6325,
    "utility_player2": 6325,
    "normalized_u1": 54.856895056374675,
    "normalized_u2": 54.856895056374675,
    "harmonic_mean": 54.856895056374675,
    "normalized_harmonic_mean": 54.856895056374675,
    "pareto_optimum": null,
    "by": "Player 1",
    "turn": 4
  },
  "max_weight": 9322,
  "scores": {
    "player1_score": 6325,
    "player2_score": 6325,
    "normalized_u1": 54.856895056374675,
    "normalized_u2": 54.856895056374675,
    "harmonic_mean": 54.856895056374675,
    "normalized_harmonic_mean": 54.856895056374675,
    "episode_score": 25.0,
    "pareto_optimum": null,
    "pareto_adherence_rate": null
  },
  "max_u1": 11530,
  "max_u2": 11530,
  "max_harmonic": 1,
  "nb_proposals": 5,
  "player1_optimum": {
    "items": [
      "A23",
      "A34",
      "A48",
      "A50",
      "A65",
      "A74",
      "A90",
      "B27",
      "B44",
      "B49",
      "B54",
      "C12",
      "C13",
      "C22",
      "C23",
      "C33",
      "C51",
      "C61",
      "C72",
      "C77",
      "C90",
      "C98",
      "C99"
    ],
    "utility_player1": 11530,
    "utility_player2": 11530,
    "pareto_optimum": null
  },
  "player2_optimum": {
    "items": [
      "A23",
      "A34",
      "A48",
      "A50",
      "A65",
      "A74",
      "A90",
      "B27",
      "B44",
      "B49",
      "B54",
      "C12",
      "C13",
      "C22",
      "C23",
      "C33",
      "C51",
      "C61",
      "C72",
      "C77",
      "C90",
      "C98",
      "C99"
    ],
    "utility_player1": 11530,
    "utility_player2": 11530,
    "pareto_optimum": null
  },
  "global_optimum": null
}